{"tgs":1,"v":"5.5.2","fr":60,"ip":0,"op":1,"w":512,"h":512,"nm":"Comp 1","ddd":0,"assets":[{"id":"comp_0","layers":[{"ddd":0,"ind":1,"ty":3,"nm":"▽ Artboard","sr":1,"ks":{"p":{"a":0,"k":[256,256,0]},"a":{"a":0,"k":[217.6,217.6,0]}},"ao":0,"ip":0,"op":300,"st":0,"bm":0},{"ddd":0,"ind":2,"ty":4,"nm":"Shape","parent":1,"sr":1,"ks":{"p":{"a":0,"k":[217.6,215.04,0]}},"ao":0,"shapes":[{"ty":"gr","it":[{"ind":0,"ty":"sh","ks":{"a":0,"k":{"i":[[-1.711,0],[0.687,5.441],[4.446,1.764],[0.849,-1.587],[-2.56,-4.206]],"o":[[1.711,0],[-0.337,-2.985],[-2.223,-0.882],[-1.374,2.442],[2.56,4.206]],"v":[[79.495,54.286],[82.055,46.742],[75.561,35.169],[70.602,36.58],[72.825,47.977]],"c":true}},"nm":"Path 1","hd":false},{"ind":1,"ty":"sh","ks":{"a":0,"k":{"i":[[-1.747,2.056],[5.295,4.559],[0,0],[2.735,0],[1.33,-1.658],[-4.783,-4.206],[-2.954,0.029]],"o":[[2.749,-3.867],[0,0],[-2.735,-2.456],[-2.114,-0.116],[-3.072,3.853],[2.228,1.952],[2.686,0.064]],"v":[[62.208,72.359],[58.112,58.682],[58.112,58.668],[49.556,54.992],[44.073,57.447],[47.158,72.521],[55.202,75.506]],"c":true}},"nm":"Path 2","hd":false},{"ind":2,"ty":"sh","ks":{"a":0,"k":{"i":[[65.011,0],[0,-66.66],[0,0],[-64.997,0],[-25.155,0.19],[-27.028,-24.558],[2.385,2.985],[24.63,5.631],[10.779,19.131],[0.175,-4.912],[-1.222,-7.122],[0,0],[0,44.042],[-42.927,0],[0,-44.028],[0.355,-3.09],[7.869,-0.706],[-2.237,-0.353],[-4.096,-29.646],[-0.35,0.529],[0.001,21.755]],"o":[[-64.997,0],[0,0],[0,66.66],[17.287,0],[22.407,0],[2.735,2.456],[-26.516,-34.558],[-30.114,-6.825],[-2.048,-3.853],[-0.191,7.225],[0,0],[-42.927,0],[0,-44.028],[42.941,0],[0.005,3.11],[-5.807,-1.058],[-2.91,0.339],[25.654,4.912],[0.162,0.706],[10.865,-18.803],[0,-66.646]],"v":[[-10.321,-135.68],[-128,-15.006],[-128,-15.02],[-10.321,105.695],[49.22,102.168],[123.284,134.799],[127.219,131.122],[51.443,84.448],[-4.837,41.301],[-8.098,43.065],[-6.548,64.638],[-10.146,64.638],[-87.97,-15.182],[-10.146,-94.989],[67.692,-15.182],[67.167,-5.875],[42.375,-6.404],[42.038,-4.301],[89.412,46.566],[90.786,46.919],[107.372,-15.006]],"c":true}},"nm":"Path 3","hd":false},{"ty":"mm","mm":1,"nm":"Merge Paths 1","hd":false},{"ty":"fl","c":{"a":0,"k":[1,1,1,1]},"o":{"a":0,"k":100},"r":1,"bm":0,"nm":"Fill 1","hd":false},{"ty":"tr","p":{"a":0,"k":[0,0]},"a":{"a":0,"k":[0,0]},"s":{"a":0,"k":[100,100]},"r":{"a":0,"k":0},"o":{"a":0,"k":100},"sk":{"a":0,"k":0},"sa":{"a":0,"k":0},"nm":"Transform"}],"nm":"Shape","bm":0,"hd":false}],"ip":0,"op":300,"st":0,"bm":0},{"ddd":0,"ind":3,"ty":4,"nm":"Rectangle","parent":1,"sr":1,"ks":{"p":{"a":0,"k":[217.6,217.6,0]}},"ao":0,"shapes":[{"ty":"gr","it":[{"ind":0,"ty":"sh","ks":{"a":0,"k":{"i":[[90.486,0],[0,0],[0,-90.486],[0,0],[-90.486,0],[0,0],[0,90.486],[0,0]],"o":[[0,0],[-90.486,0],[0,0],[0,90.486],[0,0],[90.486,0],[0,0],[0,-90.486]],"v":[[53.76,-217.6],[-53.76,-217.6],[-217.6,-53.76],[-217.6,53.76],[-53.76,217.6],[53.76,217.6],[217.6,53.76],[217.6,-53.76]],"c":true}},"nm":"Path 1","hd":false},{"ty":"fl","c":{"a":0,"k":[1,0.549019634724,0,1]},"o":{"a":0,"k":100},"r":1,"bm":0,"nm":"Fill 1","hd":false},{"ty":"tr","p":{"a":0,"k":[0,0]},"a":{"a":0,"k":[0,0]},"s":{"a":0,"k":[100,100]},"r":{"a":0,"k":0},"o":{"a":0,"k":100},"sk":{"a":0,"k":0},"sa":{"a":0,"k":0},"nm":"Transform"}],"nm":"Rectangle","bm":0,"hd":false}],"ip":0,"op":300,"st":0,"bm":0},{"ddd":0,"ind":4,"ty":4,"nm":"Artboard 2 1","sr":1,"ks":{"p":{"a":0,"k":[256,256,0]}},"ao":0,"shapes":[{"ty":"gr","it":[{"ty":"rc","d":1,"s":{"a":0,"k":[512,512]},"p":{"a":0,"k":[0,0]},"r":{"a":0,"k":0},"nm":"Rectangle Path 1","hd":false},{"ty":"tr","p":{"a":0,"k":[0,0]},"a":{"a":0,"k":[0,0]},"s":{"a":0,"k":[100,100]},"r":{"a":0,"k":0},"o":{"a":0,"k":100},"sk":{"a":0,"k":0},"sa":{"a":0,"k":0},"nm":"Transform"}],"nm":"Artboard 2 1","bm":0,"hd":false}],"ip":0,"op":300,"st":0,"bm":0}]}],"layers":[{"ddd":0,"ind":1,"ty":0,"nm":"Artboard 2 1","refId":"comp_0","sr":1,"ks":{"p":{"a":0,"k":[256,256,0]},"a":{"a":0,"k":[256,256,0]}},"ao":0,"w":512,"h":512,"ip":0,"op":300,"st":0,"bm":0}]}